sentium
