Metadata-Version: 2.1
Name: sentium
Version: 0.0.5
Summary: Semantic Enhancement through Neural Taxonomy - an Interpretable and Understandable Model
Home-page: https://github.com/socius-org/sentibank
Author: Nick S.H Oh
Author-email: research@socius.org
License: MIT
Download-URL: https://github.com/socius-org/Sentium/archive/refs/tags/0.0.5.tar.gz
Keywords: AI,Social Science,Sentiment Analysis,Rule Based Sentiment Analysis,Sentiment Lexicon
Platform: UNKNOWN
License-File: LICENSE
